{
  "japanese": [
    {
      "display": "猫",
      "reading": "ねこ",
      "romaji": "neko",
      "romajiVariants": ["neko"]
    },
    {
      "display": "犬",
      "reading": "いぬ",
      "romaji": "inu",
      "romajiVariants": ["inu"]
    },
    {
      "display": "桜",
      "reading": "さくら",
      "romaji": "sakura",
      "romajiVariants": ["sakura"]
    },
    {
      "display": "湖",
      "reading": "みずうみ",
      "romaji": "mizumi",
      "romajiVariants": ["mizumi"]
    },
    {
      "display": "光",
      "reading": "ひかり",
      "romaji": "hikari",
      "romajiVariants": ["hikari"]
    },
    {
      "display": "風",
      "reading": "かぜ",
      "romaji": "kaze",
      "romajiVariants": ["kaze"]
    },
    {
      "display": "空",
      "reading": "そら",
      "romaji": "sora",
      "romajiVariants": ["sora"]
    }
  ],
  "english": [
    "cat",
    "dog",
    "tree",
    "bird",
    "water",
    "light",
    "wind"
  ]
}
